LICENSE
MANIFEST.in
README.md
pyproject.toml
setup.cfg
setup.py
cctk/__init__.py
cctk/array.py
cctk/ensemble.py
cctk/file.py
cctk/gaussian_file.py
cctk/group.py
cctk/helper_functions.py
cctk/lines.py
cctk/load_groups.py
cctk/mae_file.py
cctk/mol2_file.py
cctk/molecule.py
cctk/optimize.py
cctk/orca_file.py
cctk/parse_gaussian.py
cctk/parse_orca.py
cctk/pdb_file.py
cctk/point_charge.py
cctk/quasiclassical.py
cctk/si_file.py
cctk/topology.py
cctk/vibrational_mode.py
cctk/xyz_file.py
cctk.egg-info/PKG-INFO
cctk.egg-info/SOURCES.txt
cctk.egg-info/dependency_links.txt
cctk.egg-info/requires.txt
cctk.egg-info/top_level.txt
cctk/data/__init__.py
cctk/data/covalent_radii.csv
cctk/data/isotopes.csv
cctk/data/vdw_radii.csv
cctk/data/__pycache__/__init__.cpython-311.pyc
cctk/data/__pycache__/__init__.cpython-37.pyc
cctk/data/__pycache__/__init__.cpython-38.pyc
cctk/data/__pycache__/__init__.cpython-39.pyc
cctk/groups/AcH.mol2
cctk/groups/BrH.mol2
cctk/groups/CF3H.mol2
cctk/groups/CHOH.mol2
cctk/groups/ClH.mol2
cctk/groups/EtH.mol2
cctk/groups/FH.mol2
cctk/groups/HCN.mol2
cctk/groups/HCO2Me.mol2
cctk/groups/HNO2.mol2
cctk/groups/IH.mol2
cctk/groups/MeH.mol2
cctk/groups/NH3.mol2
cctk/groups/NHAcH.mol2
cctk/groups/NMe2H.mol2
cctk/groups/OH2.mol2
cctk/groups/OMeH.mol2
cctk/groups/SF5H.mol2
cctk/groups/SO3HH.mol2
cctk/groups/__init__.py
cctk/groups/iPrH.mol2
cctk/groups/tBuH.mol2
cctk/groups/__pycache__/__init__.cpython-311.pyc
cctk/groups/__pycache__/__init__.cpython-37.pyc
cctk/groups/__pycache__/__init__.cpython-39.pyc
test/test_align.py
test/test_connectivity.py
test/test_ensemble.py
test/test_freqs.py
test/test_gaussian.py
test/test_group.py
test/test_helper.py
test/test_indexing.py
test/test_mae.py
test/test_molecule.py
test/test_nmr.py
test/test_opt.py
test/test_orca.py
test/test_pdb.py
test/test_pentane.py
test/test_renumber.py
test/test_solvent_extraction.py
test/test_xyz.py