Metadata-Version: 2.1
Name: cctk
Version: 0.2.23
Summary: computational chemistry toolkit
Home-page: https://github.com/ekwan/cctk
Download-URL: https://github.com/ekwan/cctk/archive/v0.2.23.tar.gz
Author: Corin Wagen and Eugene Kwan
Author-email: corin.wagen@gmail.com
License: Apache 2.0
Classifier: Development Status :: 4 - Beta
Classifier: License :: OSI Approved :: Apache Software License
Classifier: Intended Audience :: Science/Research
Classifier: Programming Language :: Python :: 3.7
Classifier: Programming Language :: Python :: 3.8
Requires-Python: >=3.6
License-File: LICENSE
